github_chat_mcp/__init__.py
github_chat_mcp/server.py
github_chat_mcp-0.1.0.dist-info/METADATA
github_chat_mcp-0.1.0.dist-info/WHEEL
github_chat_mcp-0.1.0.dist-info/entry_points.txt
github_chat_mcp-0.1.0.dist-info/licenses/LICENSE
github_chat_mcp-0.1.0.dist-info/RECORD
