Metadata-Version: 2.4
Name: github-chat-mcp
Version: 0.1.0
Summary: GitHub Chat MCP server for analyzing GitHub repositories
Project-URL: Homepage, https://github.com/AsyncFuncAI/github-chat-mcp
Project-URL: Issues, https://github.com/AsyncFuncAI/github-chat-mcp/issues
Author-email: Sheing Ng <sng@asyncfunc.ai>
License-File: LICENSE
Requires-Python: >=3.12
Requires-Dist: mcp[cli]~=1.6.0
Requires-Dist: pydantic~=2.10.3
Requires-Dist: requests~=2.31.0
